karrio/mappers/geodis/__init__.py
karrio/mappers/geodis/mapper.py
karrio/mappers/geodis/proxy.py
karrio/mappers/geodis/settings.py
karrio/plugins/geodis/__init__.py
karrio/providers/geodis/__init__.py
karrio/providers/geodis/error.py
karrio/providers/geodis/tracking.py
karrio/providers/geodis/units.py
karrio/providers/geodis/utils.py
karrio/providers/geodis/shipment/__init__.py
karrio/providers/geodis/shipment/cancel.py
karrio/providers/geodis/shipment/create.py
karrio/schemas/geodis/__init__.py
karrio/schemas/geodis/cancel_request.py
karrio/schemas/geodis/cancel_response.py
karrio/schemas/geodis/error_response.py
karrio/schemas/geodis/shipping_request.py
karrio/schemas/geodis/shipping_response.py
karrio/schemas/geodis/tracking_request.py
karrio/schemas/geodis/tracking_response.py
karrio_geodis-2026.1.4.dist-info/METADATA
karrio_geodis-2026.1.4.dist-info/WHEEL
karrio_geodis-2026.1.4.dist-info/entry_points.txt
karrio_geodis-2026.1.4.dist-info/top_level.txt
karrio_geodis-2026.1.4.dist-info/RECORD
